pxmcmc/__init__.py
pxmcmc/forward.py
pxmcmc/mcmc.py
pxmcmc/measurements.py
pxmcmc/plotting.py
pxmcmc/prior.py
pxmcmc/saving.py
pxmcmc/transforms.py
pxmcmc/uncertainty.py
pxmcmc/utils.py
pxmcmc-1.0.1.dist-info/LICENSE
pxmcmc-1.0.1.dist-info/METADATA
pxmcmc-1.0.1.dist-info/WHEEL
pxmcmc-1.0.1.dist-info/RECORD
